mini_document_storage/client/MDSClient.py
mini_document_storage/client/MDSDocument.py
mini_document_storage/client/__init__.py
mini_document_storage-1.11.3.dist-info/licenses/LICENSE
mini_document_storage-1.11.3.dist-info/METADATA
mini_document_storage-1.11.3.dist-info/WHEEL
mini_document_storage-1.11.3.dist-info/top_level.txt
mini_document_storage-1.11.3.dist-info/RECORD
