Metadata-Version: 2.4
Name: mini-document-storage
Version: 1.11.3
Summary: Fast, inexpensive document storage backed by a standard database connector.
Author-email: Stevo Brock <StevoGTA@aol.com>
License-Expression: MIT
Project-URL: Homepage, https://github.com/StevoGTA/Mini-Document-Storage
Keywords: document storage
Classifier: Programming Language :: Python
Classifier: Programming Language :: Python :: 3
Requires-Python: >=3.9
License-File: LICENSE
Requires-Dist: aiohttp
Dynamic: license-file
